jaffle/__init__.py
jaffle/_version.py
jaffle/display.py
jaffle/functions.py
jaffle/job.py
jaffle/kernel_client.py
jaffle/kernel_manager.py
jaffle/logging.py
jaffle/pygments.py
jaffle/session.py
jaffle/shell.py
jaffle/startup.py
jaffle/status.py
jaffle/utils.py
jaffle/variables.py
jaffle/app/__init__.py
jaffle/app/base/__init__.py
jaffle/app/base/app.py
jaffle/app/base/cache.py
jaffle/app/base/config.py
jaffle/app/base/logging.py
jaffle/app/base/output.py
jaffle/app/pytest/__init__.py
jaffle/app/pytest/app.py
jaffle/app/pytest/collect.py
jaffle/app/pytest/completer.py
jaffle/app/pytest/lexer.py
jaffle/app/tornado/__init__.py
jaffle/app/tornado/app.py
jaffle/app/watchdog/__init__.py
jaffle/app/watchdog/app.py
jaffle/app/watchdog/handler.py
jaffle/command/__init__.py
jaffle/command/base.py
jaffle/command/main.py
jaffle/command/attach/__init__.py
jaffle/command/attach/command.py
jaffle/command/attach/shell.py
jaffle/command/console/__init__.py
jaffle/command/console/command.py
jaffle/command/start/__init__.py
jaffle/command/start/command.py
jaffle/command/stop/__init__.py
jaffle/command/stop/command.py
jaffle/command/tty/__init__.py
jaffle/command/tty/command.py
jaffle/config/__init__.py
jaffle/config/jaffle_config.py
jaffle/config/template_string.py
jaffle/config/value.py
jaffle/process/__init__.py
jaffle/process/process.py
jaffle/schema/config_schema.json
jaffle/tests/__init__.py
jaffle/tests/integration/__init__.py
jaffle/tests/integration/jupyter_ext/__init__.py
jaffle/tests/integration/jupyter_ext/test_jupyter_ext_example.py
jaffle/tests/integration/pytest/__init__.py
jaffle/tests/integration/pytest/test_pytest_example.py
jaffle/tests/integration/tornado_spa/__init__.py
jaffle/tests/integration/tornado_spa/test_tornado_spa_example.py
jaffle/tests/unit/__init__.py
jaffle/tests/unit/conftest.py
jaffle/tests/unit/test_display.py
jaffle/tests/unit/test_functions.py
jaffle/tests/unit/test_job.py
jaffle/tests/unit/test_kernel_client.py
jaffle2-0.2.5.dist-info/LICENSE
jaffle2-0.2.5.dist-info/METADATA
jaffle2-0.2.5.dist-info/WHEEL
jaffle2-0.2.5.dist-info/entry_points.txt
jaffle2-0.2.5.dist-info/top_level.txt
jaffle2-0.2.5.dist-info/RECORD
