Metadata-Version: 2.1
Name: jaffle2
Version: 0.2.5
Summary: Version 2 of the original Jaffle. Python app and process orchestration tool for development environment
Home-page: https://github.com/albert118/jaffle
Author: Jaffle Development Team, Albert Ferguson
Author-email: albertferguson118@gmail.com
License: UNKNOWN
Keywords: orchestration interactive process test pytest watchdog
Platform: UNKNOWN
Classifier: Development Status :: 3 - Alpha
Classifier: Environment :: Console
Classifier: Intended Audience :: Developers
Classifier: License :: OSI Approved :: BSD License
Classifier: Natural Language :: English
Classifier: Operating System :: MacOS
Classifier: Operating System :: POSIX
Classifier: Programming Language :: Python :: 3
Classifier: Programming Language :: Python :: 3.4
Classifier: Programming Language :: Python :: 3.5
Classifier: Programming Language :: Python :: 3.6
Classifier: Topic :: Software Development :: Libraries
Classifier: Topic :: Software Development :: Testing
Classifier: Topic :: System :: Monitoring
Classifier: Topic :: System :: Filesystems
Classifier: Topic :: System :: Shells
Classifier: Topic :: Utilities
License-File: LICENSE
Requires-Dist: filelock (<4,>=3.0.0)
Requires-Dist: ipython
Requires-Dist: jupyter-client
Requires-Dist: jupyter-console
Requires-Dist: jupyter-core
Requires-Dist: jsonschema (<3,>=2.0.0)
Requires-Dist: mako (<2,>=1.0.0)
Requires-Dist: notebook (<6,>=5.0.0)
Requires-Dist: prompt-toolkit (<2)
Requires-Dist: pygments
Requires-Dist: pyyaml
Requires-Dist: pyzmq
Requires-Dist: setuptools
Requires-Dist: tornado (<5,>=4.5)
Requires-Dist: traitlets
Requires-Dist: watchdog (>=0.8.0)
Provides-Extra: dev
Requires-Dist: flake8 (>=3.5.0) ; extra == 'dev'
Requires-Dist: pip ; extra == 'dev'
Requires-Dist: pytest (>=3.4.0) ; extra == 'dev'
Requires-Dist: pytest-cov (>=2.5.0) ; extra == 'dev'
Requires-Dist: pytest-tornado (>=0.4.0) ; extra == 'dev'
Requires-Dist: watchdog (>=0.8.0) ; extra == 'dev'
Provides-Extra: pytest
Requires-Dist: pytest (>=3.4.0) ; extra == 'pytest'
